mortimer/__init__.py
mortimer/_version.py
mortimer/config.py
mortimer/export.py
mortimer/forms.py
mortimer/models.py
mortimer/utils.py
mortimer/errors/__init__.py
mortimer/errors/handlers.py
mortimer/main/__init__.py
mortimer/main/routes.py
mortimer/static/__init__.py
mortimer/static/alfred3_small.png
mortimer/static/alfred3_study.png
mortimer/static/android-chrome-192x192.png
mortimer/static/android-chrome-512x512.png
mortimer/static/apple-touch-icon.png
mortimer/static/clippy.svg
mortimer/static/favicon-16x16.png
mortimer/static/favicon-32x32.png
mortimer/static/favicon.ico
mortimer/static/main.css
mortimer/static/style.css
mortimer/static/unigoe_logo.jpg
mortimer/static/unigoe_small.png
mortimer/static/unigoe_study.png
mortimer/static/futurizing_alfred_scripts/01_class_names_filled.json
mortimer/static/futurizing_alfred_scripts/02_function_names_filled.json
mortimer/static/futurizing_alfred_scripts/03_parameter_names_filled.json
mortimer/static/futurizing_alfred_scripts/04_attribute_names_filled.json
mortimer/static/futurizing_alfred_scripts/05_variable_names_filled.json
mortimer/static/futurizing_alfred_scripts/06_custom_modifications.json
mortimer/static/json/__init__.py
mortimer/static/json/social_media_user_agents.json
mortimer/templates/about.html
mortimer/templates/account.html
mortimer/templates/create_experiment.html
mortimer/templates/data.html
mortimer/templates/exp_inactive.html
mortimer/templates/exp_preview.html
mortimer/templates/experiment.html
mortimer/templates/experiment_config.html
mortimer/templates/experiment_log.html
mortimer/templates/experiment_script.html
mortimer/templates/export.html
mortimer/templates/futurize_script.html
mortimer/templates/home.html
mortimer/templates/impressum.html
mortimer/templates/layout.html
mortimer/templates/layout_experiment.html
mortimer/templates/layout_old.html
mortimer/templates/login.html
mortimer/templates/manage_resources.html
mortimer/templates/new_experiment_version.html
mortimer-0.9.0.dist-info/METADATA
mortimer-0.9.0.dist-info/WHEEL
mortimer-0.9.0.dist-info/top_level.txt
mortimer-0.9.0.dist-info/RECORD
