Metadata-Version: 2.1
Name: mortimer
Version: 0.9.0
Summary: A web-appication for the administration of alfred experiments.
Home-page: https://github.com/ctreffe/mortimer
Author: Christian Treffenstädt, Paul Wiemann, Johannes Brachem
Author-email: alfred@psych.uni-goettingen.de
License: UNKNOWN
Platform: UNKNOWN
Classifier: Programming Language :: Python :: 3
Classifier: License :: OSI Approved :: MIT License
Classifier: Operating System :: OS Independent
Requires-Python: >=3.7
Requires-Dist: alfred3 >=2.0.0
Requires-Dist: alfred3-interact >=0.2.4
Requires-Dist: cryptography >=3.4
Requires-Dist: email-validator >=1.1
Requires-Dist: itsdangerous >=2.1.2
Requires-Dist: flask >=1.1.2
Requires-Dist: flask-bcrypt >=0.7.1
Requires-Dist: flask-dropzone >=1.5.4
Requires-Dist: flask-login >=0.5.0
Requires-Dist: flask-mail >=0.9.1
Requires-Dist: flask-mongoengine >=0.9.5
Requires-Dist: flask-wtf >=0.14.3
Requires-Dist: pymongo >=3.10
Requires-Dist: python-dotenv
